gcpfemu/__init__.py
gcpfemu/serve.py
gcp_functions_emulator-0.1.8.dist-info/LICENSE
gcp_functions_emulator-0.1.8.dist-info/METADATA
gcp_functions_emulator-0.1.8.dist-info/WHEEL
gcp_functions_emulator-0.1.8.dist-info/entry_points.txt
gcp_functions_emulator-0.1.8.dist-info/top_level.txt
gcp_functions_emulator-0.1.8.dist-info/RECORD
